setup.py
src/typhoonae/__init__.py
src/typhoonae.redis.egg-info/PKG-INFO
src/typhoonae.redis.egg-info/SOURCES.txt
src/typhoonae.redis.egg-info/dependency_links.txt
src/typhoonae.redis.egg-info/not-zip-safe
src/typhoonae.redis.egg-info/requires.txt
src/typhoonae.redis.egg-info/top_level.txt
src/typhoonae/redis/__init__.py
src/typhoonae/redis/datastore_redis_stub.py
src/typhoonae/redis/indexes.py
src/typhoonae/redis/tests/__init__.py
src/typhoonae/redis/tests/benchmark.py
src/typhoonae/redis/tests/test_datastore_redis.py
src/typhoonae/redis/tests/test_indexes.py