Metadata-Version: 1.0
Name: typhoonae.redis
Version: 0.1.0b1
Summary: Typhoon App Engine Redis Datastore.
Home-page: http://code.google.com/p/typhoonae/source/checkout?repo=redis
Author: Tobias Rodaebel
Author-email: tobias dot rodaebel at googlemail dot com
License: Apache License 2.0
Keywords: gae,appengine,redis,datastore,typhoonae,tae
Platform: UNKNOWN
Classifier: Development Status :: 4 - Beta
Classifier: Environment :: Web Environment
Classifier: Intended Audience :: Developers
Classifier: License :: OSI Approved :: Apache Software License
Classifier: Natural Language :: English
Classifier: Operating System :: MacOS :: MacOS X
Classifier: Operating System :: POSIX :: Linux
Classifier: Programming Language :: Python
